fhir_cda/__init__.py
fhir_cda/core.py
fhir_cda/utils.py
fhir_cda/annotator/__init__.py
fhir_cda/annotator/abstract_annotator.py
fhir_cda/annotator/measurement_annotator.py
fhir_cda/annotator/process_annotator.py
fhir_cda/annotator/tool_annotator.py
fhir_cda/annotator/workflow_annotator.py
fhir_cda/ehr/__init__.py
fhir_cda/ehr/elements.py
fhir_cda/ehr/measurement.py
fhir_cda/ehr/workflow.py
fhir_cda/terms/__init__.py
fhir_cda/terms/knowledgebase.py
fhir_cda-1.2.5.dist-info/licenses/LICENSE
fhir_cda-1.2.5.dist-info/WHEEL
fhir_cda-1.2.5.dist-info/METADATA
fhir_cda-1.2.5.dist-info/RECORD
