Metadata-Version: 2.4
Name: fhir_cda
Version: 1.2.5
Summary: Clinic Description Annotator for FHIR and SPARC
Keywords: fhir,SPARC,Clinic Description Annotator
Author-email: Linkun Gao <gaolinkun123@gmail.com>
Requires-Python: >=3.9
Classifier: Development Status :: 5 - Production/Stable
Classifier: Environment :: Web Environment
Classifier: Intended Audience :: Developers
Classifier: Operating System :: OS Independent
Classifier: Programming Language :: Python
Classifier: Programming Language :: Python :: 3
Classifier: Programming Language :: Python :: 3.9
Classifier: Programming Language :: Python :: 3.10
Classifier: Programming Language :: Python :: 3.11
Classifier: Programming Language :: Python :: 3.12
Classifier: Topic :: Internet :: WWW/HTTP
Classifier: Topic :: Software Development :: Libraries :: Python Modules
License-File: LICENSE
Requires-Dist: pydicom==2.4.4
Requires-Dist: pyyaml==6.0.2
Requires-Dist: pathlib==1.0.1
Requires-Dist: pandas>=2.3.3
Requires-Dist: openpyxl>=3.1.5
Requires-Dist: pytest>=6.2.4 ; extra == "test"
Project-URL: Documentation, https://github.com/ABI-CTT-Group/clinical-description-annotator#readme
Project-URL: Homepage, https://github.com/ABI-CTT-Group/clinical-description-annotator
Project-URL: Source, https://github.com/ABI-CTT-Group/clinical-description-annotator.git
Provides-Extra: test
